[
    {
        "name": "Apple iPhone 11",
        "description": "Smartphone with advanced camera features and iOS operating system.",
        "price": 699.99,
        "discount": 10,
        "stock": 30,
        "brand": "Apple",
        "category": "Electronics"
    },
    {
        "name": "Sony PlayStation 4",
        "description": "Gaming console with a wide range of popular games and entertainment features.",
        "price": 299.99,
        "discount": 15,
        "stock": 20,
        "brand": "Sony",
        "category": "Gaming"
    },
    {
        "name": "Nike Air Max 90",
        "description": "Classic athletic sneakers known for their comfort and style.",
        "price": 119.99,
        "discount": 5,
        "stock": 50,
        "brand": "Nike",
        "category": "Footwear"
    },
    {
        "name": "Canon EOS 5D Mark IV",
        "description": "High-end digital camera favored by professional photographers.",
        "price": 2499.99,
        "discount": 10,
        "stock": 39,
        "brand": "Canon",
        "category": "Cameras"
    },
    {
        "name": "Samsung 55-Inch 4K Smart TV",
        "description": "Television with 4K Ultra HD resolution and smart TV capabilities.",
        "price": 799.99,
        "discount": 8,
        "stock": 35,
        "brand": "Samsung",
        "category": "Electronics"
    },
    {
        "name": "Calvin Klein Eternity Perfume",
        "description": "Fragrance known for its timeless and elegant scent.",
        "price": 69.99,
        "discount": 0,
        "stock": 45,
        "brand": "Calvin Klein",
        "category": "Perfumes"
    },
    {
        "name": "HP Envy x360 Laptop",
        "description": "Convertible laptop with a touchscreen display for versatility.",
        "price": 849.99,
        "discount": 12,
        "stock": 38,
        "brand": "HP",
        "category": "Laptops"
    },
    {
        "name": "Adidas UltraBoost Running Shoes",
        "description": "High-performance running shoes designed for comfort and speed.",
        "price": 129.99,
        "discount": 5,
        "stock": 55,
        "brand": "Adidas",
        "category": "Footwear"
    },
    {
        "name": "Amazon Echo Dot (3rd Gen)",
        "description": "Smart speaker with Alexa voice control for home automation.",
        "price": 39.99,
        "discount": 20,
        "stock": 40,
        "brand": "Amazon",
        "category": "Electronics"
    },
    {
        "name": "Fujifilm Instax Mini 9 Instant Camera",
        "description": "Compact instant camera for capturing memories on the go.",
        "price": 69.99,
        "discount": 8,
        "stock": 32,
        "brand": "Fujifilm",
        "category": "Cameras"
    },
    {
        "name": "Calvin Klein CK One Cologne",
        "description": "Unisex fragrance with a clean and refreshing scent.",
        "price": 49.99,
        "discount": 0,
        "stock": 30,
        "brand": "Calvin Klein",
        "category": "Cologne"
    },
    {
        "name": "Sony 65-Inch 4K OLED TV",
        "description": "High-quality OLED TV with stunning picture and sound quality.",
        "price": 1999.99,
        "discount": 5,
        "stock": 42,
        "brand": "Sony",
        "category": "Electronics"
    },
    {
        "name": "Microsoft Surface Pro 7",
        "description": "Versatile 2-in-1 laptop and tablet for productivity and creativity.",
        "price": 1199.99,
        "discount": 10,
        "stock": 37,
        "brand": "Microsoft",
        "category": "Laptops"
    },
    {
        "name": "Casio G-Shock Watch",
        "description": "Rugged and durable digital watch known for its toughness.",
        "price": 99.99,
        "discount": 0,
        "stock": 47,
        "brand": "Casio",
        "category": "Watches"
    },
    {
        "name": "Bose QuietComfort 35 II Headphones",
        "description": "Wireless noise-canceling headphones for immersive audio experiences.",
        "price": 299.99,
        "discount": 10,
        "stock": 58,
        "brand": "Bose",
        "category": "Electronics"
    },
    {
        "name": "Dior J'adore Perfume",
        "description": "Luxurious and elegant fragrance with floral and fruity notes.",
        "price": 149.99,
        "discount": 0,
        "stock": 70,
        "brand": "Dior",
        "category": "Perfumes"
    },
    {
        "name": "Canon EOS Rebel T6 DSLR Camera",
        "description": "Entry-level DSLR camera with high-quality image capture capabilities.",
        "price": 499.99,
        "discount": 15,
        "stock": 80,
        "brand": "Canon",
        "category": "Cameras"
    },
    {
        "name": "Asus ROG Strix Gaming Laptop",
        "description": "High-performance gaming laptop with dedicated graphics for gamers.",
        "price": 1499.99,
        "discount": 5,
        "stock": 95,
        "brand": "Asus",
        "category": "Laptops"
    },
    {
        "name": "Puma Clyde Court Basketball Shoes",
        "description": "Basketball shoes designed for optimal performance and style on the court.",
        "price": 119.99,
        "discount": 5,
        "stock": 90,
        "brand": "Puma",
        "category": "Footwear"
    },
    {
        "name": "LG OLED65C9PUA 65-Inch 4K OLED TV",
        "description": "Top-of-the-line OLED TV with exceptional picture quality and smart features.",
        "price": 2799.99,
        "discount": 8,
        "stock": 100,
        "brand": "LG",
        "category": "Electronics"
    },
    {
        "name": "Gucci Guilty Perfume",
        "description": "Sensual and seductive fragrance with floral and oriental notes.",
        "price": 89.99,
        "discount": 0,
        "stock": 105,
        "brand": "Gucci",
        "category": "Perfumes"
    },
    {
        "name": "Sony PlayStation 5",
        "description": "Gaming console with a wide range of popular games and entertainment features.",
        "price": 500.99,
        "discount": 10,
        "stock": 68,
        "brand": "Sony",
        "category": "Electronics"
    },
    {
        "name": "Nikon D850 DSLR Camera",
        "description": "High-resolution DSLR camera for professional photographers and enthusiasts.",
        "price": 2999.99,
        "discount": 10,
        "stock": 52,
        "brand": "Nikon",
        "category": "Cameras"
    },
    {
        "name": "Nike Zoom Pegasus 38 Running Shoes",
        "description": "Versatile and comfortable running shoes for athletes of all levels.",
        "price": 129.99,
        "discount": 5,
        "stock": 115,
        "brand": "Nike",
        "category": "Footwear"
    },
    {
        "name": "Samsung 75-Inch QLED 4K Smart TV",
        "description": "Large QLED TV with stunning visuals and smart features for home entertainment.",
        "price": 1999.99,
        "discount": 8,
        "stock": 68,
        "brand": "Samsung",
        "category": "Electronics"
    },
    {
        "name": "Versace Eros Cologne",
        "description": "A bold and masculine fragrance with oriental and woody notes.",
        "price": 79.99,
        "discount": 0,
        "stock": 110,
        "brand": "Versace",
        "category": "Cologne"
    },
    {
        "name": "Panasonic Lumix GH5 Mirrorless Camera",
        "description": "High-performance mirrorless camera with 4K video recording capabilities.",
        "price": 1799.99,
        "discount": 5,
        "stock": 120,
        "brand": "Panasonic",
        "category": "Cameras"
    },
    {
        "name": "Samsung Galaxy S21 Ultra",
        "description": "Flagship smartphone with an advanced camera system and 5G connectivity.",
        "price": 1299.99,
        "discount": 10,
        "stock": 125,
        "brand": "Samsung",
        "category": "Electronics"
    },
    {
        "name": "Rolex Daytona Watch",
        "description": "Iconic luxury watch known for its precision and style.",
        "price": 19999.99,
        "discount": 0,
        "stock": 135,
        "brand": "Rolex",
        "category": "Watches"
    },
    {
        "name": "Adidas Originals Superstar Sneakers",
        "description": "Classic sneakers with a timeless design and iconic three stripes.",
        "price": 79.99,
        "discount": 10,
        "stock": 145,
        "brand": "Adidas",
        "category": "Footwear"
    },
    {
        "name": "Sony WH-1000XM4 Wireless Headphones",
        "description": "Premium wireless headphones with industry-leading noise-canceling technology.",
        "price": 349.99,
        "discount": 10,
        "stock": 78,
        "brand": "Sony",
        "category": "Electronics"
    },
    {
        "name": "Estée Lauder Advanced Night Repair Serum",
        "description": "Highly regarded skincare serum known for its rejuvenating properties.",
        "price": 79.99,
        "discount": 0,
        "stock": 130,
        "brand": "Estée Lauder",
        "category": "Beauty"
    },
    {
        "name": "LG OLED77C1PUA 77-Inch 4K OLED TV",
        "description": "Premium OLED TV with cinematic picture quality and smart features.",
        "price": 3499.99,
        "discount": 8,
        "stock": 135,
        "brand": "LG",
        "category": "Electronics"
    },
    {
        "name": "Canon EOS Rebel T7i DSLR Camera",
        "description": "Versatile DSLR camera with great image quality for photography enthusiasts.",
        "price": 799.99,
        "discount": 12,
        "stock": 88,
        "brand": "Canon",
        "category": "Cameras"
    },
    {
        "name": "Nike Air Force 1 Sneakers",
        "description": "Classic and iconic sneakers known for their comfort and style.",
        "price": 89.99,
        "discount": 5,
        "stock": 140,
        "brand": "Nike",
        "category": "Footwear"
    },
    {
        "name": "Bose SoundLink Revolve+ Portable Speaker",
        "description": "Portable Bluetooth speaker with 360-degree sound for music enthusiasts.",
        "price": 299.99,
        "discount": 10,
        "stock": 145,
        "brand": "Bose",
        "category": "Electronics"
    },
    {
        "name": "Yves Saint Laurent Black Opium Perfume",
        "description": "Sensual and addictive fragrance with coffee and vanilla notes.",
        "price": 129.99,
        "discount": 0,
        "stock": 98,
        "brand": "Yves Saint Laurent",
        "category": "Perfumes"
    },
    {
        "name": "Acer Predator Helios 300 Gaming Laptop",
        "description": "High-performance gaming laptop with dedicated graphics for gamers.",
        "price": 1399.99,
        "discount": 8,
        "stock": 72,
        "brand": "Acer",
        "category": "Laptops"
    },
    {
        "name": "Dyson V11 Absolute Cordless Vacuum",
        "description": "Powerful cordless vacuum cleaner with advanced cleaning technology.",
        "price": 599.99,
        "discount": 15,
        "stock": 150,
        "brand": "Dyson",
        "category": "Appliances"
    },
    {
        "name": "GoPro HERO9 Black Action Camera",
        "description": "High-quality action camera for capturing adventures and outdoor activities.",
        "price": 449.99,
        "discount": 10,
        "stock": 155,
        "brand": "GoPro",
        "category": "Cameras"
    },
    {
        "name": "MAC Ruby Woo Lipstick",
        "description": "Iconic red lipstick known for its bold and classic color.",
        "price": 19.99,
        "discount": 0,
        "stock": 160,
        "brand": "MAC",
        "category": "Beauty"
    },
    {
        "name": "Levi's 501 Original Fit Jeans",
        "description": "Timeless and classic denim jeans known for their quality and style.",
        "price": 49.99,
        "discount": 5,
        "stock": 170,
        "brand": "Levi's",
        "category": "Apparel"
    },
    {
        "name": "JBL Flip 5 Portable Bluetooth Speaker",
        "description": "Compact and waterproof speaker for music on the go.",
        "price": 99.99,
        "discount": 10,
        "stock": 165,
        "brand": "JBL",
        "category": "Electronics"
    },
    {
        "name": "Giorgio Armani Acqua di Gio Cologne",
        "description": "Fresh and aquatic fragrance for men with citrus and woodsy notes.",
        "price": 79.99,
        "discount": 0,
        "stock": 82,
        "brand": "Giorgio Armani",
        "category": "Cologne"
    },
    {
        "name": "KitchenAid Artisan Stand Mixer",
        "description": "Iconic kitchen appliance for baking and cooking enthusiasts.",
        "price": 349.99,
        "discount": 8,
        "stock": 92,
        "brand": "KitchenAid",
        "category": "Appliances"
    }
]